{
  "storage_features": {
    "raid_technologies": {
      "basic_raid": [
        "RAID 0 - Striping for performance",
        "RAID 1 - Mirroring for redundancy",
        "RAID 5 - Distributed parity",
        "RAID 6 - Double distributed parity",
        "RAID 10 - Striped mirrors"
      ],
      "advanced_raid": [
        "RAID 50 - Striped RAID 5 arrays",
        "RAID 60 - Striped RAID 6 arrays",
        "RAID 1E - Enhanced mirroring",
        "RAID 5E - Enhanced distributed parity",
        "RAID 5EE - Enhanced distributed parity with hot spare"
      ],
      "enterprise_features": [
        "Hot spare management",
        "Online capacity expansion",
        "RAID level migration",
        "Background rebuild",
        "Predictive failure analysis"
      ]
    },
    "storage_protocols": {
      "high_speed": [
        "NVMe 2.0 with 64K queues",
        "NVMe over Fabrics (NVMe-oF)",
        "Fibre Channel 32Gbps",
        "InfiniBand EDR/HDR",
        "PCIe 5.0/6.0"
      ],
      "enterprise_protocols": [
        "iSCSI with TCP offload",
        "FCoE with DCB support",
        "RoCE with congestion control",
        "SAS 24Gbps",
        "SATA 6Gbps"
      ],
      "emerging_protocols": [
        "NVMe over TCP",
        "NVMe over RDMA",
        "Storage over IP",
        "Ethernet storage fabric",
        "Compute Express Link (CXL)"
      ]
    },
    "data_protection": {
      "encryption": [
        "AES-256 encryption at rest",
        "TLS 1.3 for data in transit",
        "Key management integration",
        "Hardware acceleration",
        "Compliance certifications"
      ],
      "redundancy": [
        "Multiple data copies",
        "Geographic distribution",
        "Synchronous replication",
        "Asynchronous replication",
        "Point-in-time recovery"
      ],
      "backup_recovery": [
        "Incremental backups",
        "Differential backups",
        "Full system backups",
        "Bare metal recovery",
        "Disaster recovery planning"
      ]
    },
    "performance_optimization": {
      "caching": [
        "Multi-tier caching",
        "Read-ahead algorithms",
        "Write-back caching",
        "Cache coherency",
        "Intelligent prefetching"
      ],
      "tiering": [
        "Automated tiering",
        "Performance-based placement",
        "Cost optimization",
        "Workload awareness",
        "Dynamic rebalancing"
      ],
      "optimization": [
        "Thin provisioning",
        "Data deduplication",
        "Compression algorithms",
        "Parallel I/O processing",
        "Load balancing"
      ]
    }
  },
  "compute_features": {
    "processor_architectures": {
      "modern_processors": [
        "Multi-socket configurations",
        "High core counts (64+ cores)",
        "Advanced vector instructions",
        "Large cache hierarchies",
        "Power efficiency features"
      ],
      "specialized_accelerators": [
        "GPU compute acceleration",
        "FPGA programmability",
        "ASIC optimization",
        "Neural network processors",
        "Quantum computing interfaces"
      ],
      "enterprise_features": [
        "Hardware virtualization support",
        "Advanced security features",
        "Reliability engineering",
        "Thermal management",
        "Power management"
      ]
    },
    "memory_technologies": {
      "high_performance": [
        "DDR5 with ECC",
        "High bandwidth memory (HBM)",
        "Non-volatile DIMMs",
        "Intel Optane persistent memory",
        "Multi-channel configurations"
      ],
      "enterprise_features": [
        "Memory mirroring",
        "Memory sparing",
        "Hot-plug memory",
        "Memory encryption",
        "Memory scrubbing"
      ],
      "emerging_technologies": [
        "Compute Express Link (CXL)",
        "Gen-Z memory fabric",
        "Optical interconnects",
        "3D stacked memory",
        "Phase-change memory"
      ]
    },
    "system_capabilities": {
      "virtualization": [
        "Hardware-assisted virtualization",
        "Nested virtualization",
        "Live migration",
        "Resource overcommitment",
        "Virtual machine management"
      ],
      "composability": [
        "Dynamic resource allocation",
        "Workload-aware provisioning",
        "Resource pooling",
        "Policy-based management",
        "Automated optimization"
      ],
      "high_availability": [
        "Clustering support",
        "Failover capabilities",
        "Load balancing",
        "Health monitoring",
        "Predictive maintenance"
      ]
    }
  },
  "networking_features": {
    "high_speed_networking": {
      "ethernet": [
        "100Gbps Ethernet",
        "400Gbps Ethernet",
        "800Gbps Ethernet",
        "Terabit Ethernet",
        "Multi-rate support"
      ],
      "specialized_protocols": [
        "InfiniBand EDR/HDR",
        "Fibre Channel 32Gbps",
        "Omni-Path Architecture",
        "Cray Slingshot",
        "Custom interconnects"
      ],
      "emerging_technologies": [
        "Silicon photonics",
        "Coherent optics",
        "Space-division multiplexing",
        "Quantum networking",
        "Neuromorphic interconnects"
      ]
    },
    "network_optimization": {
      "performance": [
        "RDMA over Converged Ethernet",
        "TCP offload engines",
        "Network function virtualization",
        "Software-defined networking",
        "Network slicing"
      ],
      "quality_of_service": [
        "Traffic prioritization",
        "Bandwidth reservation",
        "Latency guarantees",
        "Jitter control",
        "Packet loss prevention"
      ],
      "security": [
        "Network encryption",
        "Access control lists",
        "Intrusion detection",
        "DDoS protection",
        "Network segmentation"
      ]
    }
  },
  "management_features": {
    "centralized_management": {
      "infrastructure": [
        "Single pane of glass",
        "Multi-vendor support",
        "Policy-based management",
        "Automated provisioning",
        "Configuration management"
      ],
      "monitoring": [
        "Real-time monitoring",
        "Predictive analytics",
        "Performance trending",
        "Capacity planning",
        "Alert management"
      ],
      "automation": [
        "Workflow automation",
        "Self-healing systems",
        "Intelligent orchestration",
        "API-driven management",
        "Integration frameworks"
      ]
    },
    "security_management": {
      "access_control": [
        "Role-based access control",
        "Multi-factor authentication",
        "Single sign-on integration",
        "Privileged access management",
        "Audit logging"
      ],
      "compliance": [
        "Regulatory compliance",
        "Security standards",
        "Policy enforcement",
        "Risk assessment",
        "Incident response"
      ],
      "threat_protection": [
        "Advanced threat detection",
        "Behavioral analytics",
        "Machine learning security",
        "Zero-trust architecture",
        "Security automation"
      ]
    }
  },
  "sustainability_features": {
    "energy_efficiency": {
      "power_management": [
        "Dynamic power scaling",
        "Intelligent power capping",
        "Power-aware scheduling",
        "Energy-efficient algorithms",
        "Renewable energy integration"
      ],
      "thermal_management": [
        "Advanced cooling systems",
        "Liquid cooling support",
        "Thermal-aware placement",
        "Heat recovery systems",
        "Environmental monitoring"
      ],
      "efficiency_metrics": [
        "Power usage effectiveness (PUE)",
        "Data center infrastructure efficiency",
        "Carbon footprint tracking",
        "Energy cost optimization",
        "Sustainability reporting"
      ]
    },
    "environmental_responsibility": {
      "materials": [
        "Recyclable components",
        "Sustainable sourcing",
        "Reduced packaging",
        "Longevity design",
        "End-of-life planning"
      ],
      "operations": [
        "Waste reduction",
        "Water conservation",
        "Emissions control",
        "Biodiversity protection",
        "Community engagement"
      ]
    }
  },
  "innovation_features": {
    "artificial_intelligence": {
      "machine_learning": [
        "Predictive analytics",
        "Anomaly detection",
        "Performance optimization",
        "Resource allocation",
        "Automated decision making"
      ],
      "ai_acceleration": [
        "GPU compute clusters",
        "Tensor processing units",
        "Neural network processors",
        "AI-optimized storage",
        "Intelligent networking"
      ],
      "ai_integration": [
        "Natural language processing",
        "Computer vision",
        "Speech recognition",
        "Recommendation engines",
        "Autonomous systems"
      ]
    },
    "edge_computing": {
      "edge_optimization": [
        "Compact form factors",
        "Power efficiency",
        "Environmental resilience",
        "Local processing",
        "Edge intelligence"
      ],
      "distributed_computing": [
        "Fog computing",
        "Mobile edge computing",
        "Multi-access edge computing",
        "Edge orchestration",
        "Edge security"
      ]
    },
    "quantum_computing": {
      "quantum_ready": [
        "Quantum algorithm support",
        "Quantum-safe cryptography",
        "Quantum-classical hybrid",
        "Quantum networking",
        "Quantum error correction"
      ]
    }
  },
  "presentation_enhancements": {
    "visual_elements": [
      "Professional formatting",
      "Color-coded status indicators",
      "Progress bars and spinners",
      "Rich text formatting",
      "Table layouts"
    ],
    "interactive_features": [
      "Real-time generation",
      "Live validation",
      "Quality scoring",
      "Scenario selection",
      "Audience participation"
    ],
    "demonstration_ready": [
      "Enterprise-grade output",
      "Professional appearance",
      "Comprehensive coverage",
      "High-quality validation",
      "Standards compliance"
    ]
  }
}
